pypi_wrangler/__init__.py
pypi_wrangler/wrangle.py
pypi_wrangler-1.0.0.dist-info/METADATA
pypi_wrangler-1.0.0.dist-info/WHEEL
pypi_wrangler-1.0.0.dist-info/top_level.txt
pypi_wrangler-1.0.0.dist-info/RECORD
